exoplasimlegacy/Alderaan_surf_0129.sra
exoplasimlegacy/Alderaan_surf_0172.sra
exoplasimlegacy/COPYING
exoplasimlegacy/Example_surf_0129.sra
exoplasimlegacy/Example_surf_0172.sra
exoplasimlegacy/FAQ
exoplasimlegacy/Mountains_surf_0129.sra
exoplasimlegacy/Mountains_surf_0172.sra
exoplasimlegacy/NEW_IN_VERSION_17
exoplasimlegacy/PlanetGrid-Mountains.ipynb
exoplasimlegacy/PlanetGrid.ipynb
exoplasimlegacy/README
exoplasimlegacy/README_COUPLING_PLASIM_PUMA
exoplasimlegacy/README_MAC_USER
exoplasimlegacy/README_UBUNTU
exoplasimlegacy/README_WINDOWS_USER
exoplasimlegacy/T21.nc
exoplasimlegacy/__init__.py
exoplasimlegacy/cc_check.c
exoplasimlegacy/cleancat
exoplasimlegacy/cleanplasim
exoplasimlegacy/cleanpuma
exoplasimlegacy/cleansam
exoplasimlegacy/cmdpuma
exoplasimlegacy/compile.sh
exoplasimlegacy/configure.sh
exoplasimlegacy/csub.c
exoplasimlegacy/f90check.f90
exoplasimlegacy/filesupport.py
exoplasimlegacy/gcmt.py
exoplasimlegacy/index.html
exoplasimlegacy/make_most
exoplasimlegacy/makecheck
exoplasimlegacy/makedebug
exoplasimlegacy/makestellarspec.py
exoplasimlegacy/most.c
exoplasimlegacy/pyburn.py
exoplasimlegacy/pyfft.f90
exoplasimlegacy/randomcontinents.py
exoplasimlegacy/samplemtplanet.jpg
exoplasimlegacy/samplemtplanet.png
exoplasimlegacy/sampleplanet.jpg
exoplasimlegacy/Cat_UG_00/app_codestruct.tex
exoplasimlegacy/Cat_UG_00/app_modulsvariables.tex
exoplasimlegacy/Cat_UG_00/app_namelists.tex
exoplasimlegacy/Cat_UG_00/cat_ug.aux
exoplasimlegacy/Cat_UG_00/cat_ug.bbl
exoplasimlegacy/Cat_UG_00/cat_ug.blg
exoplasimlegacy/Cat_UG_00/cat_ug.log
exoplasimlegacy/Cat_UG_00/cat_ug.pdf
exoplasimlegacy/Cat_UG_00/cat_ug.tex
exoplasimlegacy/Cat_UG_00/cat_ug.toc
exoplasimlegacy/Cat_UG_00/chap_cathist.tex
exoplasimlegacy/Cat_UG_00/chap_catoutput.tex
exoplasimlegacy/Cat_UG_00/chap_evoleq.tex
exoplasimlegacy/Cat_UG_00/chap_impcat.tex
exoplasimlegacy/Cat_UG_00/chap_modifycat.tex
exoplasimlegacy/Cat_UG_00/chap_pseudospec.tex
exoplasimlegacy/Cat_UG_00/chap_runcat.tex
exoplasim_legacy-3.0.0a18.dist-info/LICENSE.TXT
exoplasim_legacy-3.0.0a18.dist-info/METADATA
exoplasim_legacy-3.0.0a18.dist-info/WHEEL
exoplasim_legacy-3.0.0a18.dist-info/top_level.txt
exoplasim_legacy-3.0.0a18.dist-info/RECORD
