Metadata-Version: 2.1
Name: exoplasim-legacy
Version: 3.0.0a18
Summary: Exoplanet GCM
Home-page: https://github.com/alphaparrot/ExoPlaSim
Author: Adiv Paradise
Author-email: paradise.astro@gmail.com
License: GNU General Public License
Platform: UNKNOWN
Provides-Extra: netCDF4
Provides-Extra: HDF5
